lyricsfetcher/__init__.py
lyricsfetcher/__main__.py
lyricsfetcher/docopt.py
lyricsfetcher/fetcher_helper.py
lyricsfetcher/genius_token.conf
lyricsfetcher/lyricsfetcher.py
lyricsfetcher/outdir.conf
lyrics_fetcher-0.2.2.dist-info/LICENSE.txt
lyrics_fetcher-0.2.2.dist-info/METADATA
lyrics_fetcher-0.2.2.dist-info/WHEEL
lyrics_fetcher-0.2.2.dist-info/entry_points.txt
lyrics_fetcher-0.2.2.dist-info/top_level.txt
lyrics_fetcher-0.2.2.dist-info/RECORD
