Metadata-Version: 2.1
Name: lyrics-fetcher
Version: 0.2.2
Summary: Fetch lyrics from Genius using your command line
Home-page: https://github.com/JelleHubertse/lyrics-fetcher
Author: Jelle Hubertse
License: GNU GPLv3
Keywords: lyrics,genius,CLI
Platform: UNKNOWN
Classifier: Development Status :: 4 - Beta
Classifier: Programming Language :: Python :: 3
Classifier: Programming Language :: Python :: 3.6
Classifier: Programming Language :: Python :: 3.7
Classifier: Programming Language :: Python :: 3.8
Classifier: Programming Language :: Python :: 3.9
Classifier: Operating System :: MacOS :: MacOS X
Classifier: Environment :: MacOS X
Classifier: License :: OSI Approved :: GNU General Public License v3 (GPLv3)
Classifier: Natural Language :: English
Requires-Python: >3.6
Requires-Dist: lyricsgenius (>=2.0.2)
Requires-Dist: docopt (>=0.6)
